[
    [],
    [
        {
            "id": "0",
            "ang": "86",
            "dst": "25"
        },
        {
            "id": "0",
            "ang": "42",
            "dst": "31"
        },
        {
            "id": "0",
            "ang": "20",
            "dst": "119"
        }
    ],
    [],
    [
        {
            "id": "0",
            "ang": "122",
            "dst": "8"
        },
        {
            "id": "0",
            "ang": "88",
            "dst": "25"
        },
        {
            "id": "0",
            "ang": "42",
            "dst": "54"
        },
        {
            "id": "0",
            "ang": "18",
            "dst": "1"
        }
    ],
    [],
    [],
    [],
    [],
    [],
    [],
    [],
    []
]
